askOmi/__init__.py
askomi-0.8.5.dist-info/METADATA
askomi-0.8.5.dist-info/WHEEL
askomi-0.8.5.dist-info/top_level.txt
askomi-0.8.5.dist-info/RECORD
