Metadata-Version: 2.4
Name: askOmi
Version: 0.8.5
Summary: Hi Cutie
Author: Why Should I reveal
Dynamic: author
Dynamic: description
Dynamic: description-content-type
Dynamic: summary
